{
  "abre": "open",
  "actividades": "activities",
  "activos": "assets",
  "además": "besides",
  "adquirir": "acquire",
  "alcohol": "alcohol",
  "algún": "some",
  "alimenta": "feed",
  "almacenar": "store",
  "amazonia": "amazonia",
  "ambiental": "environmental",
  "américa": "america",
  "anillo": "ring",
  "anonimato": "anonymity",
  "aprobó": "approved",
  "aquí": "here",
  "arrojan": "they throw",
  "artículo": "article",
  "artículos": "articles",
  "aumentar": "increase",
  "aumentarlo": "increase it",
  "aéreas": "aerial",
  "bancaria": "banking",
  "bancos": "banks",
  "beneficia": "benefit",
  "blanqueamiento": "whitening",
  "blanquear": "whiten",
  "brasil": "brazil",
  "buscan": "search",
  "básicos": "basic",
  "caja": "box",
  "cambio": "change",
  "capone": "capone",
  "capos": "bosses",
  "causas": "causes",
  "centrales": "central",
  "cerca": "fence",
  "ceremonial": "ceremonial",
  "certificado": "certificate",
  "cianuro": "cyanide",
  "cientos": "hundreds",
  "clandestinas": "clandestine",
  "clásico": "classic",
  "coinciden": "match",
  "colocación": "placement",
  "colombia": "colombia",
  "comenzado": "started",
  "comenzó": "began",
  "comercial": "commercial",
  "comercializadoras": "marketers",
  "complicar": "complicate",
  "composición": "composition",
  "compra": "buy",
  "compran": "they buy",
  "compras": "shopping",
  "compuestos": "compounds",
  "concepto": "concept",
  "condenaron": "they condemned",
  "condiciones": "conditions",
  "conectar": "connect",
  "conoce": "know",
  "conquistaron": "they conquered",
  "consecuencias": "consequences",
  "consideraba": "considered",
  "constantes": "constants",
  "contables": "accountants",
  "contadores": "accountants",
  "contaminar": "contaminate",
  "contener": "contain",
  "control": "[translation needed]",
  "convertirlo": "convert",
  "corona": "crown",
  "costo": "cost",
  "creación": "creation",
  "crear": "create",
  "criminal": "[translation needed]",
  "criminales": "criminals",
  "cuenta": "account",
  "deforestación": "deforestation",
  "dejar": "leave",
  "delincuentes": "criminals",
  "delito": "crime",
  "denuncias": "complaints",
  "depositaban": "deposited",
  "depositan": "deposit",
  "desaparecer": "disappear",
  "descubra": "discover",
  "detectar": "detect",
  "detenga": "stop",
  "diamantes": "diamonds",
  "dieron": "they gave",
  "diferencia": "difference",
  "dios": "god",
  "directamente": "directly",
  "distintas": "distinct",
  "divino": "divine",
  "divisas": "foreign exchange",
  "droga": "drug",
  "drogas": "drugs",
  "dólar": "dollar",
  "dólares": "dollars",
  "económico": "economic",
  "efectivo": "cash",
  "ejemplo": "example",
  "elemento": "element",
  "embargo": "[translation needed]",
  "empezaron": "they started",
  "empresa": "enterprise",
  "empresas": "companies",
  "encontró": "found",
  "enorme": "huge",
  "enormemente": "enormously",
  "enriqueció": "enriched",
  "entender": "to understand",
  "entra": "enter",
  "esfuerzos": "efforts",
  "española": "spanish",
  "especialmente": "especially",
  "esquema": "scheme",
  "estaba": "was",
  "establecieron": "established",
  "estados": "states",
  "estará": "will be",
  "estatal": "state",
  "estratificación": "stratification",
  "estudios": "studies",
  "está": "this",
  "europeos": "europeans",
  "evitar": "avoid",
  "expertos": "experts",
  "explotación": "exploitation",
  "explotar": "blow",
  "exportarlo": "export it",
  "extendido": "extended",
  "extracción": "extraction",
  "fachada": "facade",
  "famoso": "famous",
  "fascinado": "fascinated",
  "fase": "phase",
  "federal": "federal",
  "ferocidad": "ferocity",
  "financiación": "financing",
  "financiero": "financial",
  "fiscal": "fiscal",
  "flujo": "flow",
  "forma": "shape",
  "fraude": "fraud",
  "fronteras": "borders",
  "fuente": "[translation needed]",
  "fuentes": "[translation needed]",
  "fueran": "were",
  "fuerzas": "forces",
  "funciona": "works",
  "fundaciones": "foundations",
  "futuro": "future",
  "ganancias": "earnings",
  "generar": "trigger",
  "gente": "people",
  "gradualmente": "gradually",
  "gramos": "grams",
  "grupos": "groups",
  "hace": "does",
  "hacen": "do",
  "hecho": "made",
  "herramientas": "tools",
  "humanos": "humans",
  "ilegal": "illegal",
  "ilegales": "illegal",
  "ilícitas": "illicit",
  "ilícito": "illicit",
  "impacto": "impact",
  "implican": "imply",
  "impuestos": "taxes",
  "inestabilidad": "instability",
  "infantil": "children's",
  "ingresos": "income",
  "instalado": "installed",
  "instalan": "install",
  "insuficientes": "insufficient",
  "integración": "integration",
  "integral": "[translation needed]",
  "intermediarios": "intermediaries",
  "internacionales": "international",
  "interrumpir": "interrupt",
  "introduce": "[translation needed]",
  "inversiones": "investments",
  "invertir": "invest",
  "involucrados": "involved",
  "jefe": "boss",
  "junto": "together",
  "latina": "[translation needed]",
  "lavado": "washing",
  "lavanderías": "laundries",
  "lavar": "[translation needed]",
  "legales": "legal",
  "legaliza": "legalize",
  "legalizar": "legalize",
  "legítimos": "legitimate",
  "lejos": "far",
  "letales": "lethal",
  "libros": "books",
  "limpiaban": "they cleaned",
  "lingote": "ingot",
  "llama": "[translation needed]",
  "llegan": "they arrive",
  "llegar": "arrive",
  "locales": "[translation needed]",
  "lograr": "achieve",
  "lujo": "luxury",
  "mafia": "[translation needed]",
  "maleable": "malleable",
  "manera": "manner",
  "mantiene": "maintains",
  "mantienen": "keep",
  "mayoría": "most",
  "mercados": "markets",
  "mercurio": "[translation needed]",
  "metal": "[translation needed]",
  "milenios": "millennia",
  "miles": "[translation needed]",
  "minas": "[translation needed]",
  "minera": "mining",
  "mineras": "mining",
  "minería": "mining",
  "ministerio": "ministry",
  "mitad": "half",
  "moneda": "currency",
  "montaña": "mountain",
  "mundo": "world",
  "máximo": "maximum",
  "métodos": "methods",
  "méxico": "mexico",
  "narco": "[translation needed]",
  "narcotraficantes": "drug traffickers",
  "narcotráfico": "drug trafficking",
  "necesitaban": "they needed",
  "necesitan": "need",
  "nefastas": "harmful",
  "negocio": "business",
  "negocios": "business",
  "objeto": "object",
  "obligó": "forced",
  "obtener": "obtain",
  "obtiene": "gets",
  "onza": "[translation needed]",
  "onzas": "ounces",
  "organizaciones": "organizations",
  "origen": "[translation needed]",
  "pagado": "paid",
  "pagarlo": "pay it",
  "partes": "parts",
  "pasos": "steps",
  "países": "countries",
  "peces": "pieces",
  "perfecto": "perfect",
  "permite": "allows",
  "personales": "personal",
  "perú": "peru",
  "pistas": "clues",
  "precioso": "precious",
  "prehispánicos": "pre-hispanic",
  "principal": "[translation needed]",
  "principales": "main",
  "principios": "beginning",
  "proceso": "process",
  "prohibido": "forbidden",
  "práctica": "practice",
  "pueblos": "[translation needed]",
  "puntos": "points",
  "puramente": "purely",
  "química": "chemical",
  "rastreables": "[translation needed]",
  "rastrear": "track",
  "rastreo": "tracking",
  "rastro": "trail",
  "recibos": "receipts",
  "recibían": "they received",
  "reforzar": "reinforce",
  "refugio": "[translation needed]",
  "registros": "records",
  "región": "region",
  "regresa": "come back",
  "regulado": "regulated",
  "regulares": "regular",
  "remover": "[translation needed]",
  "reserva": "[translation needed]",
  "respaldar": "support",
  "resultar": "result",
  "ricas": "rich",
  "riesgo": "risk",
  "riqueza": "wealth",
  "ropa": "clothes",
  "rubro": "category",
  "sacrificar": "sacrifice",
  "salud": "health",
  "seca": "[translation needed]",
  "sedimentos": "sediment",
  "seguridad": "security",
  "separar": "separate",
  "servirán": "will serve",
  "sexual": "[translation needed]",
  "siglo": "century",
  "sigue": "go on",
  "similar": "[translation needed]",
  "simplificada": "simplified",
  "sistema": "system",
  "suministros": "supplies",
  "teniendo": "having",
  "terrenal": "earthly",
  "testaferros": "figureheads",
  "tiempos": "time",
  "tierra": "[translation needed]",
  "toneladas": "tons",
  "traficaban": "trafficked",
  "transacciones": "transactions",
  "transferencias": "transfers",
  "transporta": "transport",
  "traslada": "transfer",
  "traían": "they brought",
  "ubican": "locate",
  "unidos": "joined",
  "unir": "bind",
  "usan": "they use",
  "usarse": "use",
  "utilizaban": "they used",
  "utilizarse": "be used",
  "valer": "worth",
  "valor": "[translation needed]",
  "vehículos": "vehicles",
  "vende": "to sell",
  "venezuela": "[translation needed]",
  "viene": "he comes",
  "visión": "vision",
  "zonas": "zones"
}